paramax/__init__.py
paramax/py.typed
paramax/utils.py
paramax/wrappers.py
paramax-0.0.5.dist-info/METADATA
paramax-0.0.5.dist-info/WHEEL
paramax-0.0.5.dist-info/licenses/LICENSE
paramax-0.0.5.dist-info/RECORD
