Metadata-Version: 2.4
Name: paramax
Version: 0.0.5
Summary: Parameterizations and parameter constraints for JAX PyTrees.
Project-URL: repository, https://github.com/danielward27/paramax
Project-URL: documentation, https://danielward27.github.io/paramax/index.html
Author-email: Daniel Ward <danielward27@outlook.com>
License: The MIT License (MIT)
License-File: LICENSE
Keywords: equinox,jax,neural-networks
Classifier: Intended Audience :: Science/Research
Classifier: License :: OSI Approved :: MIT License
Classifier: Natural Language :: English
Classifier: Programming Language :: Python :: 3
Classifier: Topic :: Scientific/Engineering :: Artificial Intelligence
Classifier: Topic :: Scientific/Engineering :: Information Analysis
Classifier: Topic :: Scientific/Engineering :: Mathematics
Classifier: Typing :: Typed
Requires-Python: >=3.10
Requires-Dist: equinox
Requires-Dist: jax
Requires-Dist: jaxtyping
Provides-Extra: dev
Requires-Dist: beartype; extra == 'dev'
Requires-Dist: pytest; extra == 'dev'
Requires-Dist: ruff; extra == 'dev'
Requires-Dist: sphinx; extra == 'dev'
Requires-Dist: sphinx-autodoc-typehints; extra == 'dev'
Requires-Dist: sphinx-book-theme; extra == 'dev'
Requires-Dist: sphinx-copybutton; extra == 'dev'
